drought_scan/__init__.py
drought_scan/core.py
drought_scan/utils/__init__.py
drought_scan/utils/data_io.py
drought_scan/utils/decorators.py
drought_scan/utils/drought_indices.py
drought_scan/utils/hydrology.py
drought_scan/utils/statistics.py
drought_scan/utils/visualization.py
droughtscan-3.0.7.dist-info/licenses/LICENSE
droughtscan-3.0.7.dist-info/METADATA
droughtscan-3.0.7.dist-info/WHEEL
droughtscan-3.0.7.dist-info/top_level.txt
droughtscan-3.0.7.dist-info/RECORD
