Metadata-Version: 2.4
Name: droughtscan
Version: 3.0.7
Summary: Multi-temporal and basin-scale drought analysis and monitoring
Author: Arianna Di Paola, Leandro Rocchi, Massimiliano Pasqui
Maintainer-email: Arianna Di Paola <arianna.dipaola@cnr.it>
License-Expression: GPL-3.0-or-later
Project-URL: Website, https://droughtcentral.it/
Project-URL: Team, https://droughtcentral.it/team/
Project-URL: Homepage, https://github.com/PyDipa/DroughtScan
Project-URL: Repository, https://github.com/PyDipa/DroughtScan
Project-URL: Documentation, https://github.com/PyDipa/DroughtScan#readme
Requires-Python: <3.11,>=3.9
License-File: LICENSE
Requires-Dist: numpy>=1.2
Requires-Dist: pandas>=2.2
Requires-Dist: openpyxl>=3.1
Requires-Dist: matplotlib>=3.8
Requires-Dist: cmcrameri>=1.4
Requires-Dist: scipy>=1.11
Requires-Dist: geopandas>=1.0
Requires-Dist: regionmask>=0.11
Requires-Dist: netCDF4>=1.6
Requires-Dist: python-dateutil>=2.8
Provides-Extra: dev
Requires-Dist: pytest; extra == "dev"
Requires-Dist: pytest-cov; extra == "dev"
Requires-Dist: ruff; extra == "dev"
Requires-Dist: black; extra == "dev"
Requires-Dist: mypy; extra == "dev"
Requires-Dist: pre-commit; extra == "dev"
Dynamic: license-file
